<?xml version="1.0" encoding="UTF-8"?>
<!DOCTYPE mapper PUBLIC "-//mybatis.org//DTD Mapper 3.0//EN" "http://mybatis.org/dtd/mybatis-3-mapper.dtd">
<mapper namespace="com.ayang818.kugga.services.mapper.ChatContentMapper">
  <resultMap id="BaseResultMap" type="com.ayang818.kugga.services.pojo.model.ChatContent">
    <!--
      WARNING - @mbg.generated
      This element is automatically generated by MyBatis Generator, do not modify.
      This element was generated on Sun Jan 19 22:08:53 CST 2020.
    -->
    <id column="id" jdbcType="VARCHAR" property="id" />
    <result column="content" jdbcType="VARCHAR" property="content" />
    <result column="type" jdbcType="INTEGER" property="type" />
    <result column="create_time" jdbcType="TIMESTAMP" property="createTime" />
  </resultMap>
  <sql id="Example_Where_Clause">
    <!--
      WARNING - @mbg.generated
      This element is automatically generated by MyBatis Generator, do not modify.
      This element was generated on Sun Jan 19 22:08:53 CST 2020.
    -->
    <where>
      <foreach collection="oredCriteria" item="criteria" separator="or">
        <if test="criteria.valid">
          <trim prefix="(" prefixOverrides="and" suffix=")">
            <foreach collection="criteria.criteria" item="criterion">
              <choose>
                <when test="criterion.noValue">
                  and ${criterion.condition}
                </when>
                <when test="criterion.singleValue">
                  and ${criterion.condition} #{criterion.value}
                </when>
                <when test="criterion.betweenValue">
                  and ${criterion.condition} #{criterion.value} and #{criterion.secondValue}
                </when>
                <when test="criterion.listValue">
                  and ${criterion.condition}
                  <foreach close=")" collection="criterion.value" item="listItem" open="(" separator=",">
                    #{listItem}
                  </foreach>
                </when>
              </choose>
            </foreach>
          </trim>
        </if>
      </foreach>
    </where>
  </sql>
  <sql id="Update_By_Example_Where_Clause">
    <!--
      WARNING - @mbg.generated
      This element is automatically generated by MyBatis Generator, do not modify.
      This element was generated on Sun Jan 19 22:08:53 CST 2020.
    -->
    <where>
      <foreach collection="example.oredCriteria" item="criteria" separator="or">
        <if test="criteria.valid">
          <trim prefix="(" prefixOverrides="and" suffix=")">
            <foreach collection="criteria.criteria" item="criterion">
              <choose>
                <when test="criterion.noValue">
                  and ${criterion.condition}
                </when>
                <when test="criterion.singleValue">
                  and ${criterion.condition} #{criterion.value}
                </when>
                <when test="criterion.betweenValue">
                  and ${criterion.condition} #{criterion.value} and #{criterion.secondValue}
                </when>
                <when test="criterion.listValue">
                  and ${criterion.condition}
                  <foreach close=")" collection="criterion.value" item="listItem" open="(" separator=",">
                    #{listItem}
                  </foreach>
                </when>
              </choose>
            </foreach>
          </trim>
        </if>
      </foreach>
    </where>
  </sql>
  <sql id="Base_Column_List">
    <!--
      WARNING - @mbg.generated
      This element is automatically generated by MyBatis Generator, do not modify.
      This element was generated on Sun Jan 19 22:08:53 CST 2020.
    -->
    id, content, type, create_time
  </sql>
  <select id="selectByExample" parameterType="com.ayang818.kugga.services.pojo.model.ChatContentExample" resultMap="BaseResultMap">
    <!--
      WARNING - @mbg.generated
      This element is automatically generated by MyBatis Generator, do not modify.
      This element was generated on Sun Jan 19 22:08:53 CST 2020.
    -->
    select
    <if test="distinct">
      distinct
    </if>
    <include refid="Base_Column_List" />
    from chat_message_content
    <if test="_parameter != null">
      <include refid="Example_Where_Clause" />
    </if>
    <if test="orderByClause != null">
      order by ${orderByClause}
    </if>
  </select>
  <select id="selectByPrimaryKey" parameterType="java.lang.String" resultMap="BaseResultMap">
    <!--
      WARNING - @mbg.generated
      This element is automatically generated by MyBatis Generator, do not modify.
      This element was generated on Sun Jan 19 22:08:53 CST 2020.
    -->
    select 
    <include refid="Base_Column_List" />
    from chat_message_content
    where id = #{id,jdbcType=VARCHAR}
  </select>
  <delete id="deleteByPrimaryKey" parameterType="java.lang.String">
    <!--
      WARNING - @mbg.generated
      This element is automatically generated by MyBatis Generator, do not modify.
      This element was generated on Sun Jan 19 22:08:53 CST 2020.
    -->
    delete from chat_message_content
    where id = #{id,jdbcType=VARCHAR}
  </delete>
  <delete id="deleteByExample" parameterType="com.ayang818.kugga.services.pojo.model.ChatContentExample">
    <!--
      WARNING - @mbg.generated
      This element is automatically generated by MyBatis Generator, do not modify.
      This element was generated on Sun Jan 19 22:08:53 CST 2020.
    -->
    delete from chat_message_content
    <if test="_parameter != null">
      <include refid="Example_Where_Clause" />
    </if>
  </delete>
  <insert id="insert" parameterType="com.ayang818.kugga.services.pojo.model.ChatContent">
    <!--
      WARNING - @mbg.generated
      This element is automatically generated by MyBatis Generator, do not modify.
      This element was generated on Sun Jan 19 22:08:53 CST 2020.
    -->
    insert into chat_message_content (id, content, type, 
      create_time)
    values (#{id,jdbcType=VARCHAR}, #{content,jdbcType=VARCHAR}, #{type,jdbcType=INTEGER}, 
      #{createTime,jdbcType=TIMESTAMP})
  </insert>
  <insert id="insertSelective" parameterType="com.ayang818.kugga.services.pojo.model.ChatContent">
    <!--
      WARNING - @mbg.generated
      This element is automatically generated by MyBatis Generator, do not modify.
      This element was generated on Sun Jan 19 22:08:53 CST 2020.
    -->
    insert into chat_message_content
    <trim prefix="(" suffix=")" suffixOverrides=",">
      <if test="id != null">
        id,
      </if>
      <if test="content != null">
        content,
      </if>
      <if test="type != null">
        type,
      </if>
      <if test="createTime != null">
        create_time,
      </if>
    </trim>
    <trim prefix="values (" suffix=")" suffixOverrides=",">
      <if test="id != null">
        #{id,jdbcType=VARCHAR},
      </if>
      <if test="content != null">
        #{content,jdbcType=VARCHAR},
      </if>
      <if test="type != null">
        #{type,jdbcType=INTEGER},
      </if>
      <if test="createTime != null">
        #{createTime,jdbcType=TIMESTAMP},
      </if>
    </trim>
  </insert>
  <select id="countByExample" parameterType="com.ayang818.kugga.services.pojo.model.ChatContentExample" resultType="java.lang.Long">
    <!--
      WARNING - @mbg.generated
      This element is automatically generated by MyBatis Generator, do not modify.
      This element was generated on Sun Jan 19 22:08:53 CST 2020.
    -->
    select count(*) from chat_message_content
    <if test="_parameter != null">
      <include refid="Example_Where_Clause" />
    </if>
  </select>
  <update id="updateByExampleSelective" parameterType="map">
    <!--
      WARNING - @mbg.generated
      This element is automatically generated by MyBatis Generator, do not modify.
      This element was generated on Sun Jan 19 22:08:53 CST 2020.
    -->
    update chat_message_content
    <set>
      <if test="record.id != null">
        id = #{record.id,jdbcType=VARCHAR},
      </if>
      <if test="record.content != null">
        content = #{record.content,jdbcType=VARCHAR},
      </if>
      <if test="record.type != null">
        type = #{record.type,jdbcType=INTEGER},
      </if>
      <if test="record.createTime != null">
        create_time = #{record.createTime,jdbcType=TIMESTAMP},
      </if>
    </set>
    <if test="_parameter != null">
      <include refid="Update_By_Example_Where_Clause" />
    </if>
  </update>
  <update id="updateByExample" parameterType="map">
    <!--
      WARNING - @mbg.generated
      This element is automatically generated by MyBatis Generator, do not modify.
      This element was generated on Sun Jan 19 22:08:53 CST 2020.
    -->
    update chat_message_content
    set id = #{record.id,jdbcType=VARCHAR},
      content = #{record.content,jdbcType=VARCHAR},
      type = #{record.type,jdbcType=INTEGER},
      create_time = #{record.createTime,jdbcType=TIMESTAMP}
    <if test="_parameter != null">
      <include refid="Update_By_Example_Where_Clause" />
    </if>
  </update>
  <update id="updateByPrimaryKeySelective" parameterType="com.ayang818.kugga.services.pojo.model.ChatContent">
    <!--
      WARNING - @mbg.generated
      This element is automatically generated by MyBatis Generator, do not modify.
      This element was generated on Sun Jan 19 22:08:53 CST 2020.
    -->
    update chat_message_content
    <set>
      <if test="content != null">
        content = #{content,jdbcType=VARCHAR},
      </if>
      <if test="type != null">
        type = #{type,jdbcType=INTEGER},
      </if>
      <if test="createTime != null">
        create_time = #{createTime,jdbcType=TIMESTAMP},
      </if>
    </set>
    where id = #{id,jdbcType=VARCHAR}
  </update>
  <update id="updateByPrimaryKey" parameterType="com.ayang818.kugga.services.pojo.model.ChatContent">
    <!--
      WARNING - @mbg.generated
      This element is automatically generated by MyBatis Generator, do not modify.
      This element was generated on Sun Jan 19 22:08:53 CST 2020.
    -->
    update chat_message_content
    set content = #{content,jdbcType=VARCHAR},
      type = #{type,jdbcType=INTEGER},
      create_time = #{createTime,jdbcType=TIMESTAMP}
    where id = #{id,jdbcType=VARCHAR}
  </update>
  <select id="selectByExampleWithRowbounds" parameterType="com.ayang818.kugga.services.pojo.model.ChatContentExample" resultMap="BaseResultMap">
    <!--
      WARNING - @mbg.generated
      This element is automatically generated by MyBatis Generator, do not modify.
      This element was generated on Sun Jan 19 22:08:53 CST 2020.
    -->
    select
    <if test="distinct">
      distinct
    </if>
    <include refid="Base_Column_List" />
    from chat_message_content
    <if test="_parameter != null">
      <include refid="Example_Where_Clause" />
    </if>
    <if test="orderByClause != null">
      order by ${orderByClause}
    </if>
  </select>
</mapper>